{
	"name": "ropensci registry",
	"version": 0.1,
	"packages": [
		{
			"name": "alm",
			"type": "package",
			"status": "good",
			"category": "biology"
		},
		{
			"name": "AntWeb",
			"type": "package",
			"status": "good",
			"category": "biology"
		},
		{
			"name": "aRxiv",
			"type": "package",
			"status": "good",
			"category": "biology"
		},
		{
			"name": "bmc",
			"type": "package",
			"status": "good",
			"category": "biology"
		},
		{
			"name": "bold",
			"type": "package",
			"status": "good",
			"category": "biology"
		},
		{
			"name": "citeulike",
			"type": "package",
			"status": "deprecated",
			"category": "biology"
		},
		{
			"name": "clifro",
			"type": "package",
			"status": "good",
			"category": "biology"
		},
		{
			"name": "datapackage",
			"type": "package",
			"status": "good",
			"category": "biology"
		},
		{
			"name": "dependencies",
			"type": "package",
			"status": "good",
			"category": "biology"
		},
		{
			"name": "dvn",
			"type": "package",
			"status": "good",
			"category": "biology"
		},
		{
			"name": "ecoengine",
			"type": "package",
			"status": "good",
			"category": "biology"
		},
		{
			"name": "ecoretriever",
			"type": "package",
			"status": "good",
			"category": "biology"
		},
		{
			"name": "elastic",
			"type": "package",
			"status": "good",
			"category": "biology"
		},
		{
			"name": "elife",
			"type": "package",
			"status": "deprecated",
			"category": "biology"
		},
		{
			"name": "EML",
			"type": "package",
			"status": "good",
			"category": "biology"
		},
		{
			"name": "floras",
			"type": "package",
			"status": "good",
			"category": "biology"
		},
		{
			"name": "fulltext",
			"type": "package",
			"status": "good",
			"category": "biology"
		},
		{
			"name": "gender",
			"type": "package",
			"status": "good",
			"category": "history"
		},
		{
			"name": "geonames",
			"type": "package",
			"status": "good",
			"category": "biology"
		},
		{
			"name": "gigadb",
			"type": "package",
			"status": "good",
			"category": "biology"
		},
		{
			"name": "gistr",
			"type": "package",
			"status": "good",
			"category": "biology"
		},
		{
			"name": "git2r",
			"type": "package",
			"status": "good",
			"category": "biology"
		},
		{
			"name": "gitr",
			"type": "package",
			"status": "good",
			"category": "biology"
		},
		{
			"name": "historydata",
			"type": "package",
			"status": "good",
			"category": "history"
		},
		{
			"name": "ICES",
			"type": "package",
			"status": "good",
			"category": "biology"
		},
		{
			"name": "IEEER",
			"type": "package",
			"status": "good",
			"category": "biology"
		},
		{
			"name": "mdextract",
			"type": "package",
			"status": "good",
			"category": "biology"
		},
		{
			"name": "mocker",
			"type": "package",
			"status": "good",
			"category": "biology"
		},
		{
			"name": "neotoma",
			"type": "package",
			"status": "good",
			"category": "biology"
		},
		{
			"name": "ots",
			"type": "package",
			"status": "good",
			"category": "biology"
		},
		{
			"name": "paleobioDB",
			"type": "package",
			"status": "good",
			"category": "biology"
		},
		{
			"name": "pangaear",
			"type": "package",
			"status": "good",
			"category": "biology"
		},
		{
			"name": "pleiades",
			"type": "package",
			"status": "good",
			"category": "biology"
		},
		{
			"name": "plotly",
			"type": "package",
			"status": "good",
			"category": "biology"
		},
		{
			"name": "prism",
			"type": "package",
			"status": "good",
			"category": "biology"
		},
		{
			"name": "rAltmetric",
			"type": "package",
			"status": "good",
			"category": "biology"
		},
		{
			"name": "rAvis",
			"type": "package",
			"status": "good",
			"category": "biology"
		},
		{
			"name": "rbefdata",
			"type": "package",
			"status": "good",
			"category": "biology"
		},
		{
			"name": "rbhl",
			"type": "package",
			"status": "good",
			"category": "biology"
		},
		{
			"name": "rbison",
			"type": "package",
			"status": "good",
			"category": "biology"
		},
		{
			"name": "rcrossref",
			"type": "package",
			"status": "good",
			"category": "biology"
		},
		{
			"name": "RCryptsy",
			"type": "package",
			"status": "good",
			"category": "biology"
		},
		{
			"name": "rDat",
			"type": "package",
			"status": "good",
			"category": "biology"
		},
		{
			"name": "rdatacite",
			"type": "package",
			"status": "good",
			"category": "biology"
		},
		{
			"name": "rdataone",
			"type": "package",
			"status": "good",
			"category": "biology"
		},
		{
			"name": "rdryad",
			"type": "package",
			"status": "good",
			"category": "biology"
		},
		{
			"name": "rebi",
			"type": "package",
			"status": "good",
			"category": "biology"
		},
		{
			"name": "rebird",
			"type": "package",
			"status": "good",
			"category": "biology"
		},
		{
			"name": "reml",
			"type": "package",
			"status": "good",
			"category": "biology"
		},
		{
			"name": "rentrez",
			"type": "package",
			"status": "good",
			"category": "biology"
		},
		{
			"name": "reol",
			"type": "package",
			"status": "good",
			"category": "biology"
		},
		{
			"name": "rfigshare",
			"type": "package",
			"status": "good",
			"category": "biology"
		},
		{
			"name": "rfishbase",
			"type": "package",
			"status": "good",
			"category": "biology"
		},
		{
			"name": "rfisheries",
			"type": "package",
			"status": "good",
			"category": "biology"
		},
		{
			"name": "rflybase",
			"type": "package",
			"status": "deprecated",
			"category": "biology"
		},
		{
			"name": "rgauges",
			"type": "package",
			"status": "good",
			"category": "biology"
		},
		{
			"name": "rgbif",
			"type": "package",
			"status": "good",
			"category": "biology"
		},
		{
			"name": "rglobi",
			"type": "package",
			"status": "good",
			"category": "biology"
		},
		{
			"name": "rgpdd",
			"type": "package",
			"status": "good",
			"category": "biology"
		},
		{
			"name": "rhindawi",
			"type": "package",
			"status": "deprecated",
			"category": "biology"
		},
		{
			"name": "rImpactStory",
			"type": "package",
			"status": "deprecated",
			"category": "biology"
		},
		{
			"name": "rinat",
			"type": "package",
			"status": "good",
			"category": "biology"
		},
		{
			"name": "ritis",
			"type": "package",
			"status": "deprecated",
			"category": "biology"
		},
		{
			"name": "rMaps",
			"type": "package",
			"status": "good",
			"category": "biology"
		},
		{
			"name": "RMendeley",
			"type": "package",
			"status": "good",
			"category": "biology"
		},
		{
			"name": "rmetadata",
			"type": "package",
			"status": "good",
			"category": "biology"
		},
		{
			"name": "RMETAR",
			"type": "package",
			"status": "good",
			"category": "biology"
		},
		{
			"name": "rnbn",
			"type": "package",
			"status": "good",
			"category": "biology"
		},
		{
			"name": "RNeXML",
			"type": "package",
			"status": "good",
			"category": "biology"
		},
		{
			"name": "rnoaa",
			"type": "package",
			"status": "good",
			"category": "biology"
		},
		{
			"name": "rnpn",
			"type": "package",
			"status": "good",
			"category": "biology"
		},
		{
			"name": "rOBIS",
			"type": "package",
			"status": "good",
			"category": "biology"
		},
		{
			"name": "rorcid",
			"type": "package",
			"status": "good",
			"category": "biology"
		},
		{
			"name": "rpensoft",
			"type": "package",
			"status": "deprecated",
			"category": "biology"
		},
		{
			"name": "rplos",
			"type": "package",
			"status": "good",
			"category": "biology"
		},
		{
			"name": "rpmc",
			"type": "package",
			"status": "deprecated",
			"category": "biology"
		},
		{
			"name": "rpwt",
			"type": "package",
			"status": "good",
			"category": "biology"
		},
		{
			"name": "rrdf",
			"type": "package",
			"status": "good",
			"category": "biology"
		},
		{
			"name": "RSelenium",
			"type": "package",
			"status": "good",
			"category": "biology"
		},
		{
			"name": "rsnps",
			"type": "package",
			"status": "good",
			"category": "biology"
		},
		{
			"name": "rspringer",
			"type": "package",
			"status": "deprecated",
			"category": "biology"
		},
		{
			"name": "rtematres",
			"type": "package",
			"status": "good",
			"category": "biology"
		},
		{
			"name": "rvertnet",
			"type": "package",
			"status": "hiatus",
			"category": "biology"
		},
		{
			"name": "rWBclimate",
			"type": "package",
			"status": "good",
			"category": "biology"
		},
		{
			"name": "sandbox",
			"type": "package",
			"status": "deprecated",
			"category": "biology"
		},
		{
			"name": "sheetseeR",
			"type": "package",
			"status": "good",
			"category": "biology"
		},
		{
			"name": "solr",
			"type": "package",
			"status": "good",
			"category": "biology"
		},
		{
			"name": "spocc",
			"type": "package",
			"status": "good",
			"category": "biology"
		},
		{
			"name": "taxize",
			"type": "package",
			"status": "good",
			"category": "biology"
		},
		{
			"name": "testdat",
			"type": "package",
			"status": "good",
			"category": "biology"
		},
		{
			"name": "togeojson",
			"type": "package",
			"status": "good",
			"category": "biology"
		},
		{
			"name": "traits",
			"type": "package",
			"status": "good",
			"category": "biology"
		},
		{
			"name": "treeBASE",
			"type": "package",
			"status": "good",
			"category": "biology"
		},
		{
			"name": "ucipp",
			"type": "package",
			"status": "good",
			"category": "biology"
		},
		{
			"name": "USAboundaries",
			"type": "package",
			"status": "good",
			"category": "history"
		},
		{
			"name": "zenodo",
			"type": "package",
			"status": "good",
			"category": "biology"
		}
	]
}
